dbt/adapters/firebolt/__init__.py
dbt/adapters/firebolt/__version__.py
dbt/adapters/firebolt/column.py
dbt/adapters/firebolt/connections.py
dbt/adapters/firebolt/impl.py
dbt/adapters/firebolt/relation.py
dbt/adapters/firebolt/relation_configs/__init__.py
dbt/include/firebolt/__init__.py
dbt/include/firebolt/dbt_project.yml
dbt/include/firebolt/macros/adapters.sql
dbt/include/firebolt/macros/catalog.sql
dbt/include/firebolt/macros/adapters/apply_grants.sql
dbt/include/firebolt/macros/adapters/relation.sql
dbt/include/firebolt/macros/dbt_external_tables/create_external_table.sql
dbt/include/firebolt/macros/dbt_external_tables/dropif.sql
dbt/include/firebolt/macros/dbt_external_tables/get_external_build_plan.sql
dbt/include/firebolt/macros/materializations/clone.sql
dbt/include/firebolt/macros/materializations/materialized_view.sql
dbt/include/firebolt/macros/materializations/seed.sql
dbt/include/firebolt/macros/materializations/snapshot_merge.sql
dbt/include/firebolt/macros/materializations/table.sql
dbt/include/firebolt/macros/materializations/test.sql
dbt/include/firebolt/macros/materializations/view.sql
dbt/include/firebolt/macros/materializations/models/incremental/column_helpers.sql
dbt/include/firebolt/macros/materializations/models/incremental/incremental.sql
dbt/include/firebolt/macros/materializations/models/incremental/is_incremental.sql
dbt/include/firebolt/macros/materializations/models/incremental/merge.sql
dbt/include/firebolt/macros/materializations/models/incremental/on_schema_change.sql
dbt/include/firebolt/macros/materializations/models/incremental/strategies.sql
dbt/include/firebolt/macros/relations/materialized_view/alter.sql
dbt/include/firebolt/macros/relations/materialized_view/create.sql
dbt/include/firebolt/macros/relations/materialized_view/describe.sql
dbt/include/firebolt/macros/relations/materialized_view/drop.sql
dbt/include/firebolt/macros/relations/materialized_view/refresh.sql
dbt/include/firebolt/macros/relations/table/create.sql
dbt_firebolt-1.11.0.dist-info/LICENSE
dbt_firebolt-1.11.0.dist-info/METADATA
dbt_firebolt-1.11.0.dist-info/WHEEL
dbt_firebolt-1.11.0.dist-info/top_level.txt
dbt_firebolt-1.11.0.dist-info/RECORD
