Metadata-Version: 2.1
Name: dbt_firebolt
Version: 1.11.0
Summary: The Firebolt adapter plugin for dbt (data build tool)
Home-page: https://github.com/firebolt-db/dbt-firebolt
Author: Firebolt
Author-email: support@firebolt.io
License: Apache-2.0
Project-URL: Bug Tracker, https://github.com/firebolt-db/dbt-firebolt/issues
Classifier: License :: OSI Approved :: Apache Software License
Classifier: Operating System :: OS Independent
Classifier: Programming Language :: Python :: 3
Classifier: Programming Language :: Python :: 3 :: Only
Classifier: Programming Language :: Python :: 3.8
Classifier: Programming Language :: Python :: 3.9
Classifier: Programming Language :: Python :: 3.10
Classifier: Programming Language :: Python :: 3.11
Classifier: Programming Language :: Python :: 3.12
Requires-Python: >=3.8
License-File: LICENSE
Requires-Dist: dbt-adapters <2.0,>=1.0
Requires-Dist: dbt-core >=1.8.0
Requires-Dist: firebolt-sdk >=1.13.0
Requires-Dist: pydantic >=0.23
Provides-Extra: dev
Requires-Dist: allure-pytest ==2.* ; extra == 'dev'
Requires-Dist: dbt-tests-adapter ~=1.6 ; extra == 'dev'
Requires-Dist: mypy ==1.4.1 ; extra == 'dev'
Requires-Dist: pre-commit ==3.5.0 ; extra == 'dev'
Requires-Dist: pytest ==7.* ; extra == 'dev'
